Metadata-Version: 2.4
Name: awesome-agents
Version: 0.1.1
Summary: A microservice using FastAPI, PostgreSQL, OpenSearch, and LangChain.
Author-email: Your Name <your.email@example.com>
Requires-Python: ==3.11.*
Requires-Dist: agentops
Requires-Dist: arize-phoenix
Requires-Dist: arize-phoenix-otel
Requires-Dist: arxiv
Requires-Dist: autogen-agentchat
Requires-Dist: autogen-core
Requires-Dist: autogen-ext[openai]
Requires-Dist: azure-identity
Requires-Dist: boto3
Requires-Dist: botocore
Requires-Dist: browser-use
Requires-Dist: browser-use[memory]
Requires-Dist: chromadb
Requires-Dist: chromium
Requires-Dist: crewai-tools==0.0.1
Requires-Dist: crewai==0.95.0
Requires-Dist: datasets
Requires-Dist: duckduckgo-search
Requires-Dist: faiss-cpu==1.10.0
Requires-Dist: fastapi==0.114.0
Requires-Dist: fitz
Requires-Dist: frontend
Requires-Dist: google-adk
Requires-Dist: google-genai
Requires-Dist: grandalf
Requires-Dist: groq
Requires-Dist: haystack-ai
Requires-Dist: httpx>=0.28.1
Requires-Dist: ipywidgets
Requires-Dist: jupyterlab
Requires-Dist: lancedb
Requires-Dist: langchain-anthropic==0.3.0
Requires-Dist: langchain-aws==0.2.7
Requires-Dist: langchain-community~=0.3.2
Requires-Dist: langchain-core~=0.3.0
Requires-Dist: langchain-deepseek-official
Requires-Dist: langchain-experimental>=0.3.4
Requires-Dist: langchain-groq
Requires-Dist: langchain-huggingface
Requires-Dist: langchain-milvus
Requires-Dist: langchain-nvidia-ai-endpoints
Requires-Dist: langchain-openai>=0.3.2
Requires-Dist: langchain-qdrant
Requires-Dist: langgraph~=0.2.53
Requires-Dist: langsmith==0.3.0
Requires-Dist: litellm
Requires-Dist: llama-index
Requires-Dist: llama-index-callbacks-opik
Requires-Dist: llama-index-embeddings-azure-openai
Requires-Dist: llama-index-llms-azure-openai
Requires-Dist: llama-index-readers-web
Requires-Dist: llama-index-readers-wikipedia
Requires-Dist: llama-index-tools-wikipedia
Requires-Dist: llama-index-vector-stores-opensearch
Requires-Dist: mcp[cli]>=1.3.0
Requires-Dist: nltk
Requires-Dist: openai-agents
Requires-Dist: openinference-instrumentation-langchain
Requires-Dist: opensearch-py
Requires-Dist: opensearch-py>=2.0.0
Requires-Dist: opik
Requires-Dist: pgvector
Requires-Dist: phidata
Requires-Dist: playwright
Requires-Dist: psycopg2
Requires-Dist: pydantic-ai
Requires-Dist: pydantic>=2.0.0
Requires-Dist: pymilvus
Requires-Dist: pymupdf
Requires-Dist: qdrant-client
Requires-Dist: ragas
Requires-Dist: rank-bm25
Requires-Dist: retrying
Requires-Dist: rich
Requires-Dist: sec-api
Requires-Dist: setuptools==68.2.2
Requires-Dist: singlestoredb
Requires-Dist: smolagents
Requires-Dist: sqlalchemy>=2.0.0
Requires-Dist: strands-agents-builder==0.0.1
Requires-Dist: strands-agents-tools==0.0.1
Requires-Dist: strands-agents==0.0.1
Requires-Dist: streamlit
Requires-Dist: typing-extensions
Requires-Dist: uvicorn>=0.21.0
Requires-Dist: yfinance
Provides-Extra: dev
Requires-Dist: black>=23.0.0; extra == 'dev'
Requires-Dist: flake8>=6.0.0; extra == 'dev'
Requires-Dist: pytest-asyncio>=0.20.0; extra == 'dev'
Requires-Dist: pytest>=7.0.0; extra == 'dev'
